prusa/link/__init__.py
prusa/link/__main__.py
prusa/link/camera_governor.py
prusa/link/conditions.py
prusa/link/config.py
prusa/link/const.py
prusa/link/daemon.py
prusa/link/interesting_logger.py
prusa/link/service_discovery.py
prusa/link/util.py
prusa/link/cameras/__init__.py
prusa/link/cameras/encoders.py
prusa/link/cameras/picamera_driver.py
prusa/link/cameras/v4l2.py
prusa/link/cameras/v4l2_driver.py
prusa/link/data/prusalink-boot
prusa/link/data/prusalink.ini
prusa/link/data/image_builder/boot-message.service
prusa/link/data/image_builder/first-boot.sh
prusa/link/data/image_builder/manager-start-script.sh
prusa/link/data/image_builder/prusalink-start-script.sh
prusa/link/multi_instance/__init__.py
prusa/link/multi_instance/__main__.py
prusa/link/multi_instance/config_component.py
prusa/link/multi_instance/const.py
prusa/link/multi_instance/controller.py
prusa/link/multi_instance/ipc_queue_adapter.py
prusa/link/multi_instance/runner_component.py
prusa/link/multi_instance/web.py
prusa/link/printer_adapter/__init__.py
prusa/link/printer_adapter/auto_telemetry.py
prusa/link/printer_adapter/command.py
prusa/link/printer_adapter/command_handlers.py
prusa/link/printer_adapter/command_queue.py
prusa/link/printer_adapter/file_printer.py
prusa/link/printer_adapter/ip_updater.py
prusa/link/printer_adapter/job.py
prusa/link/printer_adapter/keepalive.py
prusa/link/printer_adapter/lcd_printer.py
prusa/link/printer_adapter/mmu_observer.py
prusa/link/printer_adapter/model.py
prusa/link/printer_adapter/print_stat_doubler.py
prusa/link/printer_adapter/print_stats.py
prusa/link/printer_adapter/printer_polling.py
prusa/link/printer_adapter/prusa_link.py
prusa/link/printer_adapter/py.typed
prusa/link/printer_adapter/special_commands.py
prusa/link/printer_adapter/state_manager.py
prusa/link/printer_adapter/telemetry_passer.py
prusa/link/printer_adapter/updatable.py
prusa/link/printer_adapter/filesystem/__init__.py
prusa/link/printer_adapter/filesystem/sd_card.py
prusalink-0.8.1.dist-info/METADATA
prusalink-0.8.1.dist-info/WHEEL
prusalink-0.8.1.dist-info/entry_points.txt
prusalink-0.8.1.dist-info/top_level.txt
prusalink-0.8.1.dist-info/RECORD
