Metadata-Version: 2.1
Name: prusalink
Version: 0.8.1
Summary: Original PrusaLink printer adapter.
Home-page: https://github.com/prusa3d/Prusa-Link
Author: PrusaLink Developers
Author-email: link@prusa3d.cz
Maintainer: PrusaLink Developers
Maintainer-email: link@prusa3d.cz
License: Freeware
Classifier: Development Status :: 4 - Beta
Classifier: Natural Language :: English
Classifier: License :: Freeware
Classifier: Operating System :: POSIX :: Linux
Classifier: Programming Language :: Python :: 3 :: Only
Requires-Python: >=3.9
Requires-Dist: prusa.connect.sdk.printer >=0.8.1
Requires-Dist: py-gcode-metadata
Requires-Dist: pip >=22.2.0
Requires-Dist: bidict ~=0.22.1
Requires-Dist: blinker ~=1.5
Requires-Dist: extendparser ~=0.3.1
Requires-Dist: jinja2-template-info ~=0.2.4
Requires-Dist: lockfile ~=0.12.2
Requires-Dist: packaging ~=23.0
Requires-Dist: PoorWSGI ~=2.5.0
Requires-Dist: pydantic ==1.10.12
Requires-Dist: pyric ~=0.1.6.3
Requires-Dist: python-daemon ~=3.0.1
Requires-Dist: python-magic ~=0.4.27
Requires-Dist: python-prctl ~=1.8.1
Requires-Dist: PyTurboJPEG ~=1.7.0
Requires-Dist: pyudev ~=0.24.0
Requires-Dist: PyYAML ~=6.0
Requires-Dist: requests >=2.31.0
Requires-Dist: sortedcontainers ~=2.4.0
Requires-Dist: unidecode ~=1.3.6
Requires-Dist: validators ~=0.20.0
Requires-Dist: zeroconf ~=0.47.4
